terminalpackagehamderber/__init__.py
terminalpackagehamderber/command_handler.py
terminalpackagehamderber/terminal.py
terminalpackagehamderber/terminal_settings.py
terminalpackagehamderber-0.0.8.dist-info/METADATA
terminalpackagehamderber-0.0.8.dist-info/WHEEL
terminalpackagehamderber-0.0.8.dist-info/licenses/LICENSE
terminalpackagehamderber-0.0.8.dist-info/RECORD
