Metadata-Version: 2.1
Name: terminalpackagehamderber
Version: 0.0.8
Summary: Terminal package
Project-URL: Homepage, https://github.com/Hamderber/TerminalPackageHamderber
Project-URL: Bug Tracker, https://github.com/Hamderber/TerminalPackageHamderber/issues
Author-email: Hamderber <hamderber@gmail.com>
License-File: LICENSE
Classifier: License :: OSI Approved :: MIT License
Classifier: Operating System :: OS Independent
Classifier: Programming Language :: Python :: 3
Requires-Python: >=3.7
